{
    "Configuration": {
        "gravity": [0, -9.8, 0],
        "sleep_linear_velocity2_threshold": 0.01,
        "sleep_angular_velocity2_threshold": 0.01,
        "sleep_time_threshold": 1.0
    },
    "RigidBodies": [
        {
            "name": "Ground",
            "tag": "",
            "ignore_collision": false,
            "kinematic": true,
            "lifetime": -1,
            "type": "box",
            "scale": [250, 10, 250],
            "position": [0, -5, 0],
            "rotation": [1, 0, 0, 0, 1, 0, 0, 0, 1],
            "mass": 10000,
            "friction": 0.5,
            "restitution": 0.5
        },
        {
            "name": "Bunny",
            "tag": "",
            "ignore_collision": false,
            "kinematic": true,
            "lifetime": -1,
            "type": "concave",
            "mesh": "D:/ClionProjects/Physics-Engine/examples/concave_demo/bunny.obj",
            "scale": [3, 3, 3],
            "position": [2, 1, 0],
            "rotation": [1, 0, 0, 0, 1, 0, 0, 0, 1],
            "mass": 100,
            "friction": 0.5,
            "restitution": 0.5
        },
        {
            "name": "",
            "tag": "",
            "ignore_collision": false,
            "kinematic": false,
            "lifetime": -1,
            "type": "box",
            "scale": [0.8, 0.8, 0.8],
            "position": [-3, 11, -2],
            "rotation": [1, 0, 0, 0, 1, 0, 0, 0, 1],
            "mass": 1,
            "friction": 0.5,
            "restitution": 0.5,
            "linear_damping": 0,
            "angular_damping": 0.8,
            "linear_velocity": [0, 0, 0],
            "angular_velocity": [0, 0, 0]
        },
        {
            "name": "",
            "tag": "",
            "ignore_collision": false,
            "kinematic": false,
            "lifetime": -1,
            "type": "sphere",
            "scale": [0.4],
            "position": [-3, 11, -1],
            "rotation": [1, 0, 0, 0, 1, 0, 0, 0, 1],
            "mass": 1,
            "friction": 0.5,
            "restitution": 0.5,
            "linear_velocity": [0, 0, 0],
            "angular_velocity": [0, 0, 0],
            "linear_damping": 0,
            "angular_damping": 0.8
        },
        {
            "name": "",
            "tag": "",
            "ignore_collision": false,
            "kinematic": false,
            "lifetime": -1,
            "type": "box",
            "scale": [0.8, 0.8, 0.8],
            "position": [-3, 11, 0],
            "rotation": [1, 0, 0, 0, 1, 0, 0, 0, 1],
            "mass": 1,
            "friction": 0.5,
            "restitution": 0.5,
            "linear_damping": 0,
            "angular_damping": 0.8,
            "linear_velocity": [0, 0, 0],
            "angular_velocity": [0, 0, 0]
        },
        {
            "name": "",
            "tag": "",
            "ignore_collision": false,
            "kinematic": false,
            "lifetime": -1,
            "type": "sphere",
            "scale": [0.4],
            "position": [-3, 11, 1],
            "rotation": [1, 0, 0, 0, 1, 0, 0, 0, 1],
            "mass": 1,
            "friction": 0.5,
            "restitution": 0.5,
            "linear_velocity": [0, 0, 0],
            "angular_velocity": [0, 0, 0],
            "linear_damping": 0,
            "angular_damping": 0.8
        },
        {
            "name": "",
            "tag": "",
            "ignore_collision": false,
            "kinematic": false,
            "lifetime": -1,
            "type": "box",
            "scale": [0.8, 0.8, 0.8],
            "position": [-3, 11, 2],
            "rotation": [1, 0, 0, 0, 1, 0, 0, 0, 1],
            "mass": 1,
            "friction": 0.5,
            "restitution": 0.5,
            "linear_damping": 0,
            "angular_damping": 0.8,
            "linear_velocity": [0, 0, 0],
            "angular_velocity": [0, 0, 0]
        },
        {
            "name": "",
            "tag": "",
            "ignore_collision": false,
            "kinematic": false,
            "lifetime": -1,
            "type": "sphere",
            "scale": [0.4],
            "position": [-3, 11, 3],
            "rotation": [1, 0, 0, 0, 1, 0, 0, 0, 1],
            "mass": 1,
            "friction": 0.5,
            "restitution": 0.5,
            "linear_velocity": [0, 0, 0],
            "angular_velocity": [0, 0, 0],
            "linear_damping": 0,
            "angular_damping": 0.8
        },
        {
            "name": "",
            "tag": "",
            "ignore_collision": false,
            "kinematic": false,
            "lifetime": -1,
            "type": "box",
            "scale": [0.8, 0.8, 0.8],
            "position": [-2, 11, -2],
            "rotation": [1, 0, 0, 0, 1, 0, 0, 0, 1],
            "mass": 1,
            "friction": 0.5,
            "restitution": 0.5,
            "linear_damping": 0,
            "angular_damping": 0.8,
            "linear_velocity": [0, 0, 0],
            "angular_velocity": [0, 0, 0]
        },
        {
            "name": "",
            "tag": "",
            "ignore_collision": false,
            "kinematic": false,
            "lifetime": -1,
            "type": "sphere",
            "scale": [0.4],
            "position": [-2, 11, -1],
            "rotation": [1, 0, 0, 0, 1, 0, 0, 0, 1],
            "mass": 1,
            "friction": 0.5,
            "restitution": 0.5,
            "linear_velocity": [0, 0, 0],
            "angular_velocity": [0, 0, 0],
            "linear_damping": 0,
            "angular_damping": 0.8
        },
        {
            "name": "",
            "tag": "",
            "ignore_collision": false,
            "kinematic": false,
            "lifetime": -1,
            "type": "box",
            "scale": [0.8, 0.8, 0.8],
            "position": [-2, 11, 0],
            "rotation": [1, 0, 0, 0, 1, 0, 0, 0, 1],
            "mass": 1,
            "friction": 0.5,
            "restitution": 0.5,
            "linear_damping": 0,
            "angular_damping": 0.8,
            "linear_velocity": [0, 0, 0],
            "angular_velocity": [0, 0, 0]
        },
        {
            "name": "",
            "tag": "",
            "ignore_collision": false,
            "kinematic": false,
            "lifetime": -1,
            "type": "sphere",
            "scale": [0.4],
            "position": [-2, 11, 1],
            "rotation": [1, 0, 0, 0, 1, 0, 0, 0, 1],
            "mass": 1,
            "friction": 0.5,
            "restitution": 0.5,
            "linear_velocity": [0, 0, 0],
            "angular_velocity": [0, 0, 0],
            "linear_damping": 0,
            "angular_damping": 0.8
        },
        {
            "name": "",
            "tag": "",
            "ignore_collision": false,
            "kinematic": false,
            "lifetime": -1,
            "type": "box",
            "scale": [0.8, 0.8, 0.8],
            "position": [-2, 11, 2],
            "rotation": [1, 0, 0, 0, 1, 0, 0, 0, 1],
            "mass": 1,
            "friction": 0.5,
            "restitution": 0.5,
            "linear_damping": 0,
            "angular_damping": 0.8,
            "linear_velocity": [0, 0, 0],
            "angular_velocity": [0, 0, 0]
        },
        {
            "name": "",
            "tag": "",
            "ignore_collision": false,
            "kinematic": false,
            "lifetime": -1,
            "type": "sphere",
            "scale": [0.4],
            "position": [-2, 11, 3],
            "rotation": [1, 0, 0, 0, 1, 0, 0, 0, 1],
            "mass": 1,
            "friction": 0.5,
            "restitution": 0.5,
            "linear_velocity": [0, 0, 0],
            "angular_velocity": [0, 0, 0],
            "linear_damping": 0,
            "angular_damping": 0.8
        },
        {
            "name": "",
            "tag": "",
            "ignore_collision": false,
            "kinematic": false,
            "lifetime": -1,
            "type": "box",
            "scale": [0.8, 0.8, 0.8],
            "position": [-1, 11, -2],
            "rotation": [1, 0, 0, 0, 1, 0, 0, 0, 1],
            "mass": 1,
            "friction": 0.5,
            "restitution": 0.5,
            "linear_damping": 0,
            "angular_damping": 0.8,
            "linear_velocity": [0, 0, 0],
            "angular_velocity": [0, 0, 0]
        },
        {
            "name": "",
            "tag": "",
            "ignore_collision": false,
            "kinematic": false,
            "lifetime": -1,
            "type": "sphere",
            "scale": [0.4],
            "position": [-1, 11, -1],
            "rotation": [1, 0, 0, 0, 1, 0, 0, 0, 1],
            "mass": 1,
            "friction": 0.5,
            "restitution": 0.5,
            "linear_velocity": [0, 0, 0],
            "angular_velocity": [0, 0, 0],
            "linear_damping": 0,
            "angular_damping": 0.8
        },
        {
            "name": "",
            "tag": "",
            "ignore_collision": false,
            "kinematic": false,
            "lifetime": -1,
            "type": "box",
            "scale": [0.8, 0.8, 0.8],
            "position": [-1, 11, 0],
            "rotation": [1, 0, 0, 0, 1, 0, 0, 0, 1],
            "mass": 1,
            "friction": 0.5,
            "restitution": 0.5,
            "linear_damping": 0,
            "angular_damping": 0.8,
            "linear_velocity": [0, 0, 0],
            "angular_velocity": [0, 0, 0]
        },
        {
            "name": "",
            "tag": "",
            "ignore_collision": false,
            "kinematic": false,
            "lifetime": -1,
            "type": "sphere",
            "scale": [0.4],
            "position": [-1, 11, 1],
            "rotation": [1, 0, 0, 0, 1, 0, 0, 0, 1],
            "mass": 1,
            "friction": 0.5,
            "restitution": 0.5,
            "linear_velocity": [0, 0, 0],
            "angular_velocity": [0, 0, 0],
            "linear_damping": 0,
            "angular_damping": 0.8
        },
        {
            "name": "",
            "tag": "",
            "ignore_collision": false,
            "kinematic": false,
            "lifetime": -1,
            "type": "box",
            "scale": [0.8, 0.8, 0.8],
            "position": [-1, 11, 2],
            "rotation": [1, 0, 0, 0, 1, 0, 0, 0, 1],
            "mass": 1,
            "friction": 0.5,
            "restitution": 0.5,
            "linear_damping": 0,
            "angular_damping": 0.8,
            "linear_velocity": [0, 0, 0],
            "angular_velocity": [0, 0, 0]
        },
        {
            "name": "",
            "tag": "",
            "ignore_collision": false,
            "kinematic": false,
            "lifetime": -1,
            "type": "sphere",
            "scale": [0.4],
            "position": [-1, 11, 3],
            "rotation": [1, 0, 0, 0, 1, 0, 0, 0, 1],
            "mass": 1,
            "friction": 0.5,
            "restitution": 0.5,
            "linear_velocity": [0, 0, 0],
            "angular_velocity": [0, 0, 0],
            "linear_damping": 0,
            "angular_damping": 0.8
        },
        {
            "name": "",
            "tag": "",
            "ignore_collision": false,
            "kinematic": false,
            "lifetime": -1,
            "type": "box",
            "scale": [0.8, 0.8, 0.8],
            "position": [0, 11, -2],
            "rotation": [1, 0, 0, 0, 1, 0, 0, 0, 1],
            "mass": 1,
            "friction": 0.5,
            "restitution": 0.5,
            "linear_damping": 0,
            "angular_damping": 0.8,
            "linear_velocity": [0, 0, 0],
            "angular_velocity": [0, 0, 0]
        },
        {
            "name": "",
            "tag": "",
            "ignore_collision": false,
            "kinematic": false,
            "lifetime": -1,
            "type": "sphere",
            "scale": [0.4],
            "position": [0, 11, -1],
            "rotation": [1, 0, 0, 0, 1, 0, 0, 0, 1],
            "mass": 1,
            "friction": 0.5,
            "restitution": 0.5,
            "linear_velocity": [0, 0, 0],
            "angular_velocity": [0, 0, 0],
            "linear_damping": 0,
            "angular_damping": 0.8
        },
        {
            "name": "",
            "tag": "",
            "ignore_collision": false,
            "kinematic": false,
            "lifetime": -1,
            "type": "box",
            "scale": [0.8, 0.8, 0.8],
            "position": [0, 11, 0],
            "rotation": [1, 0, 0, 0, 1, 0, 0, 0, 1],
            "mass": 1,
            "friction": 0.5,
            "restitution": 0.5,
            "linear_damping": 0,
            "angular_damping": 0.8,
            "linear_velocity": [0, 0, 0],
            "angular_velocity": [0, 0, 0]
        },
        {
            "name": "",
            "tag": "",
            "ignore_collision": false,
            "kinematic": false,
            "lifetime": -1,
            "type": "sphere",
            "scale": [0.4],
            "position": [0, 11, 1],
            "rotation": [1, 0, 0, 0, 1, 0, 0, 0, 1],
            "mass": 1,
            "friction": 0.5,
            "restitution": 0.5,
            "linear_velocity": [0, 0, 0],
            "angular_velocity": [0, 0, 0],
            "linear_damping": 0,
            "angular_damping": 0.8
        },
        {
            "name": "",
            "tag": "",
            "ignore_collision": false,
            "kinematic": false,
            "lifetime": -1,
            "type": "box",
            "scale": [0.8, 0.8, 0.8],
            "position": [0, 11, 2],
            "rotation": [1, 0, 0, 0, 1, 0, 0, 0, 1],
            "mass": 1,
            "friction": 0.5,
            "restitution": 0.5,
            "linear_damping": 0,
            "angular_damping": 0.8,
            "linear_velocity": [0, 0, 0],
            "angular_velocity": [0, 0, 0]
        },
        {
            "name": "",
            "tag": "",
            "ignore_collision": false,
            "kinematic": false,
            "lifetime": -1,
            "type": "sphere",
            "scale": [0.4],
            "position": [0, 11, 3],
            "rotation": [1, 0, 0, 0, 1, 0, 0, 0, 1],
            "mass": 1,
            "friction": 0.5,
            "restitution": 0.5,
            "linear_velocity": [0, 0, 0],
            "angular_velocity": [0, 0, 0],
            "linear_damping": 0,
            "angular_damping": 0.8
        },
        {
            "name": "",
            "tag": "",
            "ignore_collision": false,
            "kinematic": false,
            "lifetime": -1,
            "type": "box",
            "scale": [0.8, 0.8, 0.8],
            "position": [1, 11, -2],
            "rotation": [1, 0, 0, 0, 1, 0, 0, 0, 1],
            "mass": 1,
            "friction": 0.5,
            "restitution": 0.5,
            "linear_damping": 0,
            "angular_damping": 0.8,
            "linear_velocity": [0, 0, 0],
            "angular_velocity": [0, 0, 0]
        },
        {
            "name": "",
            "tag": "",
            "ignore_collision": false,
            "kinematic": false,
            "lifetime": -1,
            "type": "sphere",
            "scale": [0.4],
            "position": [1, 11, -1],
            "rotation": [1, 0, 0, 0, 1, 0, 0, 0, 1],
            "mass": 1,
            "friction": 0.5,
            "restitution": 0.5,
            "linear_velocity": [0, 0, 0],
            "angular_velocity": [0, 0, 0],
            "linear_damping": 0,
            "angular_damping": 0.8
        },
        {
            "name": "",
            "tag": "",
            "ignore_collision": false,
            "kinematic": false,
            "lifetime": -1,
            "type": "box",
            "scale": [0.8, 0.8, 0.8],
            "position": [1, 11, 0],
            "rotation": [1, 0, 0, 0, 1, 0, 0, 0, 1],
            "mass": 1,
            "friction": 0.5,
            "restitution": 0.5,
            "linear_damping": 0,
            "angular_damping": 0.8,
            "linear_velocity": [0, 0, 0],
            "angular_velocity": [0, 0, 0]
        },
        {
            "name": "",
            "tag": "",
            "ignore_collision": false,
            "kinematic": false,
            "lifetime": -1,
            "type": "sphere",
            "scale": [0.4],
            "position": [1, 11, 1],
            "rotation": [1, 0, 0, 0, 1, 0, 0, 0, 1],
            "mass": 1,
            "friction": 0.5,
            "restitution": 0.5,
            "linear_velocity": [0, 0, 0],
            "angular_velocity": [0, 0, 0],
            "linear_damping": 0,
            "angular_damping": 0.8
        },
        {
            "name": "",
            "tag": "",
            "ignore_collision": false,
            "kinematic": false,
            "lifetime": -1,
            "type": "box",
            "scale": [0.8, 0.8, 0.8],
            "position": [1, 11, 2],
            "rotation": [1, 0, 0, 0, 1, 0, 0, 0, 1],
            "mass": 1,
            "friction": 0.5,
            "restitution": 0.5,
            "linear_damping": 0,
            "angular_damping": 0.8,
            "linear_velocity": [0, 0, 0],
            "angular_velocity": [0, 0, 0]
        },
        {
            "name": "",
            "tag": "",
            "ignore_collision": false,
            "kinematic": false,
            "lifetime": -1,
            "type": "sphere",
            "scale": [0.4],
            "position": [1, 11, 3],
            "rotation": [1, 0, 0, 0, 1, 0, 0, 0, 1],
            "mass": 1,
            "friction": 0.5,
            "restitution": 0.5,
            "linear_velocity": [0, 0, 0],
            "angular_velocity": [0, 0, 0],
            "linear_damping": 0,
            "angular_damping": 0.8
        },
        {
            "name": "",
            "tag": "",
            "ignore_collision": false,
            "kinematic": false,
            "lifetime": -1,
            "type": "box",
            "scale": [0.8, 0.8, 0.8],
            "position": [2, 11, -2],
            "rotation": [1, 0, 0, 0, 1, 0, 0, 0, 1],
            "mass": 1,
            "friction": 0.5,
            "restitution": 0.5,
            "linear_damping": 0,
            "angular_damping": 0.8,
            "linear_velocity": [0, 0, 0],
            "angular_velocity": [0, 0, 0]
        },
        {
            "name": "",
            "tag": "",
            "ignore_collision": false,
            "kinematic": false,
            "lifetime": -1,
            "type": "sphere",
            "scale": [0.4],
            "position": [2, 11, -1],
            "rotation": [1, 0, 0, 0, 1, 0, 0, 0, 1],
            "mass": 1,
            "friction": 0.5,
            "restitution": 0.5,
            "linear_velocity": [0, 0, 0],
            "angular_velocity": [0, 0, 0],
            "linear_damping": 0,
            "angular_damping": 0.8
        },
        {
            "name": "",
            "tag": "",
            "ignore_collision": false,
            "kinematic": false,
            "lifetime": -1,
            "type": "box",
            "scale": [0.8, 0.8, 0.8],
            "position": [2, 11, 0],
            "rotation": [1, 0, 0, 0, 1, 0, 0, 0, 1],
            "mass": 1,
            "friction": 0.5,
            "restitution": 0.5,
            "linear_damping": 0,
            "angular_damping": 0.8,
            "linear_velocity": [0, 0, 0],
            "angular_velocity": [0, 0, 0]
        },
        {
            "name": "",
            "tag": "",
            "ignore_collision": false,
            "kinematic": false,
            "lifetime": -1,
            "type": "sphere",
            "scale": [0.4],
            "position": [2, 11, 1],
            "rotation": [1, 0, 0, 0, 1, 0, 0, 0, 1],
            "mass": 1,
            "friction": 0.5,
            "restitution": 0.5,
            "linear_velocity": [0, 0, 0],
            "angular_velocity": [0, 0, 0],
            "linear_damping": 0,
            "angular_damping": 0.8
        },
        {
            "name": "",
            "tag": "",
            "ignore_collision": false,
            "kinematic": false,
            "lifetime": -1,
            "type": "box",
            "scale": [0.8, 0.8, 0.8],
            "position": [2, 11, 2],
            "rotation": [1, 0, 0, 0, 1, 0, 0, 0, 1],
            "mass": 1,
            "friction": 0.5,
            "restitution": 0.5,
            "linear_damping": 0,
            "angular_damping": 0.8,
            "linear_velocity": [0, 0, 0],
            "angular_velocity": [0, 0, 0]
        },
        {
            "name": "",
            "tag": "",
            "ignore_collision": false,
            "kinematic": false,
            "lifetime": -1,
            "type": "sphere",
            "scale": [0.4],
            "position": [2, 11, 3],
            "rotation": [1, 0, 0, 0, 1, 0, 0, 0, 1],
            "mass": 1,
            "friction": 0.5,
            "restitution": 0.5,
            "linear_velocity": [0, 0, 0],
            "angular_velocity": [0, 0, 0],
            "linear_damping": 0,
            "angular_damping": 0.8
        },
        {
            "name": "",
            "tag": "",
            "ignore_collision": false,
            "kinematic": false,
            "lifetime": -1,
            "type": "box",
            "scale": [0.8, 0.8, 0.8],
            "position": [3, 11, -2],
            "rotation": [1, 0, 0, 0, 1, 0, 0, 0, 1],
            "mass": 1,
            "friction": 0.5,
            "restitution": 0.5,
            "linear_damping": 0,
            "angular_damping": 0.8,
            "linear_velocity": [0, 0, 0],
            "angular_velocity": [0, 0, 0]
        },
        {
            "name": "",
            "tag": "",
            "ignore_collision": false,
            "kinematic": false,
            "lifetime": -1,
            "type": "sphere",
            "scale": [0.4],
            "position": [3, 11, -1],
            "rotation": [1, 0, 0, 0, 1, 0, 0, 0, 1],
            "mass": 1,
            "friction": 0.5,
            "restitution": 0.5,
            "linear_velocity": [0, 0, 0],
            "angular_velocity": [0, 0, 0],
            "linear_damping": 0,
            "angular_damping": 0.8
        },
        {
            "name": "",
            "tag": "",
            "ignore_collision": false,
            "kinematic": false,
            "lifetime": -1,
            "type": "box",
            "scale": [0.8, 0.8, 0.8],
            "position": [3, 11, 0],
            "rotation": [1, 0, 0, 0, 1, 0, 0, 0, 1],
            "mass": 1,
            "friction": 0.5,
            "restitution": 0.5,
            "linear_damping": 0,
            "angular_damping": 0.8,
            "linear_velocity": [0, 0, 0],
            "angular_velocity": [0, 0, 0]
        },
        {
            "name": "",
            "tag": "",
            "ignore_collision": false,
            "kinematic": false,
            "lifetime": -1,
            "type": "sphere",
            "scale": [0.4],
            "position": [3, 11, 1],
            "rotation": [1, 0, 0, 0, 1, 0, 0, 0, 1],
            "mass": 1,
            "friction": 0.5,
            "restitution": 0.5,
            "linear_velocity": [0, 0, 0],
            "angular_velocity": [0, 0, 0],
            "linear_damping": 0,
            "angular_damping": 0.8
        },
        {
            "name": "",
            "tag": "",
            "ignore_collision": false,
            "kinematic": false,
            "lifetime": -1,
            "type": "box",
            "scale": [0.8, 0.8, 0.8],
            "position": [3, 11, 2],
            "rotation": [1, 0, 0, 0, 1, 0, 0, 0, 1],
            "mass": 1,
            "friction": 0.5,
            "restitution": 0.5,
            "linear_damping": 0,
            "angular_damping": 0.8,
            "linear_velocity": [0, 0, 0],
            "angular_velocity": [0, 0, 0]
        },
        {
            "name": "",
            "tag": "",
            "ignore_collision": false,
            "kinematic": false,
            "lifetime": -1,
            "type": "sphere",
            "scale": [0.4],
            "position": [3, 11, 3],
            "rotation": [1, 0, 0, 0, 1, 0, 0, 0, 1],
            "mass": 1,
            "friction": 0.5,
            "restitution": 0.5,
            "linear_velocity": [0, 0, 0],
            "angular_velocity": [0, 0, 0],
            "linear_damping": 0,
            "angular_damping": 0.8
        },
        {
            "name": "",
            "tag": "",
            "ignore_collision": false,
            "kinematic": false,
            "lifetime": -1,
            "type": "box",
            "scale": [0.8, 0.8, 0.8],
            "position": [4, 11, -2],
            "rotation": [1, 0, 0, 0, 1, 0, 0, 0, 1],
            "mass": 1,
            "friction": 0.5,
            "restitution": 0.5,
            "linear_damping": 0,
            "angular_damping": 0.8,
            "linear_velocity": [0, 0, 0],
            "angular_velocity": [0, 0, 0]
        },
        {
            "name": "",
            "tag": "",
            "ignore_collision": false,
            "kinematic": false,
            "lifetime": -1,
            "type": "sphere",
            "scale": [0.4],
            "position": [4, 11, -1],
            "rotation": [1, 0, 0, 0, 1, 0, 0, 0, 1],
            "mass": 1,
            "friction": 0.5,
            "restitution": 0.5,
            "linear_velocity": [0, 0, 0],
            "angular_velocity": [0, 0, 0],
            "linear_damping": 0,
            "angular_damping": 0.8
        },
        {
            "name": "",
            "tag": "",
            "ignore_collision": false,
            "kinematic": false,
            "lifetime": -1,
            "type": "box",
            "scale": [0.8, 0.8, 0.8],
            "position": [4, 11, 0],
            "rotation": [1, 0, 0, 0, 1, 0, 0, 0, 1],
            "mass": 1,
            "friction": 0.5,
            "restitution": 0.5,
            "linear_damping": 0,
            "angular_damping": 0.8,
            "linear_velocity": [0, 0, 0],
            "angular_velocity": [0, 0, 0]
        },
        {
            "name": "",
            "tag": "",
            "ignore_collision": false,
            "kinematic": false,
            "lifetime": -1,
            "type": "sphere",
            "scale": [0.4],
            "position": [4, 11, 1],
            "rotation": [1, 0, 0, 0, 1, 0, 0, 0, 1],
            "mass": 1,
            "friction": 0.5,
            "restitution": 0.5,
            "linear_velocity": [0, 0, 0],
            "angular_velocity": [0, 0, 0],
            "linear_damping": 0,
            "angular_damping": 0.8
        },
        {
            "name": "",
            "tag": "",
            "ignore_collision": false,
            "kinematic": false,
            "lifetime": -1,
            "type": "box",
            "scale": [0.8, 0.8, 0.8],
            "position": [4, 11, 2],
            "rotation": [1, 0, 0, 0, 1, 0, 0, 0, 1],
            "mass": 1,
            "friction": 0.5,
            "restitution": 0.5,
            "linear_damping": 0,
            "angular_damping": 0.8,
            "linear_velocity": [0, 0, 0],
            "angular_velocity": [0, 0, 0]
        },
        {
            "name": "",
            "tag": "",
            "ignore_collision": false,
            "kinematic": false,
            "lifetime": -1,
            "type": "sphere",
            "scale": [0.4],
            "position": [4, 11, 3],
            "rotation": [1, 0, 0, 0, 1, 0, 0, 0, 1],
            "mass": 1,
            "friction": 0.5,
            "restitution": 0.5,
            "linear_velocity": [0, 0, 0],
            "angular_velocity": [0, 0, 0],
            "linear_damping": 0,
            "angular_damping": 0.8
        },
        {
            "name": "",
            "tag": "",
            "ignore_collision": false,
            "kinematic": false,
            "lifetime": -1,
            "type": "box",
            "scale": [0.8, 0.8, 0.8],
            "position": [5, 11, -2],
            "rotation": [1, 0, 0, 0, 1, 0, 0, 0, 1],
            "mass": 1,
            "friction": 0.5,
            "restitution": 0.5,
            "linear_damping": 0,
            "angular_damping": 0.8,
            "linear_velocity": [0, 0, 0],
            "angular_velocity": [0, 0, 0]
        },
        {
            "name": "",
            "tag": "",
            "ignore_collision": false,
            "kinematic": false,
            "lifetime": -1,
            "type": "sphere",
            "scale": [0.4],
            "position": [5, 11, -1],
            "rotation": [1, 0, 0, 0, 1, 0, 0, 0, 1],
            "mass": 1,
            "friction": 0.5,
            "restitution": 0.5,
            "linear_velocity": [0, 0, 0],
            "angular_velocity": [0, 0, 0],
            "linear_damping": 0,
            "angular_damping": 0.8
        },
        {
            "name": "",
            "tag": "",
            "ignore_collision": false,
            "kinematic": false,
            "lifetime": -1,
            "type": "box",
            "scale": [0.8, 0.8, 0.8],
            "position": [5, 11, 0],
            "rotation": [1, 0, 0, 0, 1, 0, 0, 0, 1],
            "mass": 1,
            "friction": 0.5,
            "restitution": 0.5,
            "linear_damping": 0,
            "angular_damping": 0.8,
            "linear_velocity": [0, 0, 0],
            "angular_velocity": [0, 0, 0]
        },
        {
            "name": "",
            "tag": "",
            "ignore_collision": false,
            "kinematic": false,
            "lifetime": -1,
            "type": "sphere",
            "scale": [0.4],
            "position": [5, 11, 1],
            "rotation": [1, 0, 0, 0, 1, 0, 0, 0, 1],
            "mass": 1,
            "friction": 0.5,
            "restitution": 0.5,
            "linear_velocity": [0, 0, 0],
            "angular_velocity": [0, 0, 0],
            "linear_damping": 0,
            "angular_damping": 0.8
        },
        {
            "name": "",
            "tag": "",
            "ignore_collision": false,
            "kinematic": false,
            "lifetime": -1,
            "type": "box",
            "scale": [0.8, 0.8, 0.8],
            "position": [5, 11, 2],
            "rotation": [1, 0, 0, 0, 1, 0, 0, 0, 1],
            "mass": 1,
            "friction": 0.5,
            "restitution": 0.5,
            "linear_damping": 0,
            "angular_damping": 0.8,
            "linear_velocity": [0, 0, 0],
            "angular_velocity": [0, 0, 0]
        },
        {
            "name": "",
            "tag": "",
            "ignore_collision": false,
            "kinematic": false,
            "lifetime": -1,
            "type": "sphere",
            "scale": [0.4],
            "position": [5, 11, 3],
            "rotation": [1, 0, 0, 0, 1, 0, 0, 0, 1],
            "mass": 1,
            "friction": 0.5,
            "restitution": 0.5,
            "linear_velocity": [0, 0, 0],
            "angular_velocity": [0, 0, 0],
            "linear_damping": 0,
            "angular_damping": 0.8
        }
    ]
}